sopel_youtube/__init__.py
sopel_youtube-0.6.0.dist-info/COPYING
sopel_youtube-0.6.0.dist-info/METADATA
sopel_youtube-0.6.0.dist-info/WHEEL
sopel_youtube-0.6.0.dist-info/entry_points.txt
sopel_youtube-0.6.0.dist-info/top_level.txt
sopel_youtube-0.6.0.dist-info/RECORD
