Metadata-Version: 2.1
Name: sopel-youtube
Version: 0.6.0
Summary: YouTube link information plugin for Sopel.
Author-email: Else Powell <else@asinif.com>, Max Gurela <maxpowa1@gmail.com>, dgw <dgw@technobabbl.es>
Maintainer-email: dgw <dgw@technobabbl.es>
License: EFL-2.0
Project-URL: Homepage, https://github.com/sopel-irc/sopel-youtube
Project-URL: Bug Tracker, https://github.com/sopel-irc/sopel-youtube/issues
Keywords: sopel,plugin,bot,irc,youtube
Platform: Linux x86, x86-64
Classifier: Development Status :: 5 - Production/Stable
Classifier: Intended Audience :: Developers
Classifier: Intended Audience :: System Administrators
Classifier: License :: Eiffel Forum License (EFL)
Classifier: License :: OSI Approved :: Eiffel Forum License
Classifier: Operating System :: POSIX :: Linux
Classifier: Programming Language :: Python :: 3.8
Classifier: Programming Language :: Python :: 3.9
Classifier: Programming Language :: Python :: 3.10
Classifier: Programming Language :: Python :: 3.11
Classifier: Programming Language :: Python :: 3.12
Classifier: Topic :: Communications :: Chat :: Internet Relay Chat
Requires-Python: <4,>=3.8
License-File: COPYING
Requires-Dist: sopel <9,>=8.0
Requires-Dist: google-api-python-client <3,>=1.5.5
